rbczpremiumapi/__init__.py
rbczpremiumapi/api_client.py
rbczpremiumapi/api_response.py
rbczpremiumapi/configuration.py
rbczpremiumapi/exceptions.py
rbczpremiumapi/py.typed
rbczpremiumapi/rest.py
rbczpremiumapi/Model/__init__.py
rbczpremiumapi/Model/currency_list_simple.py
rbczpremiumapi/Model/download_statement_request.py
rbczpremiumapi/Model/exchange_rate.py
rbczpremiumapi/Model/exchange_rate_list.py
rbczpremiumapi/Model/get_accounts200_response.py
rbczpremiumapi/Model/get_accounts200_response_accounts_inner.py
rbczpremiumapi/Model/get_balance200_response.py
rbczpremiumapi/Model/get_balance200_response_currency_folders_inner.py
rbczpremiumapi/Model/get_balance200_response_currency_folders_inner_balances_inner.py
rbczpremiumapi/Model/get_balance401_response.py
rbczpremiumapi/Model/get_balance403_response.py
rbczpremiumapi/Model/get_balance404_response.py
rbczpremiumapi/Model/get_balance429_response.py
rbczpremiumapi/Model/get_batch_detail200_response.py
rbczpremiumapi/Model/get_batch_detail200_response_batch_items_inner.py
rbczpremiumapi/Model/get_batch_detail200_response_batch_items_inner_account_info.py
rbczpremiumapi/Model/get_batch_detail400_response.py
rbczpremiumapi/Model/get_statements200_response.py
rbczpremiumapi/Model/get_statements200_response_statements_inner.py
rbczpremiumapi/Model/get_statements400_response.py
rbczpremiumapi/Model/get_statements_request.py
rbczpremiumapi/Model/get_transaction_list200_response.py
rbczpremiumapi/Model/get_transaction_list200_response_transactions_inner.py
rbczpremiumapi/Model/get_transaction_list200_response_transactions_inner_amount.py
rbczpremiumapi/Model/get_transaction_list200_response_transactions_inner_bank_transaction_code.py
rbczpremiumapi/Model/get_transaction_list200_response_transactions_inner_entry_details.py
rbczpremiumapi/Model/get_transaction_list200_response_transactions_inner_entry_details_transaction_details.py
rbczpremiumapi-1.0.2.dist-info/licenses/AUTHORS.md
rbczpremiumapi-1.0.2.dist-info/licenses/LICENSE
rbczpremiumapi-1.0.2.dist-info/METADATA
rbczpremiumapi-1.0.2.dist-info/WHEEL
rbczpremiumapi-1.0.2.dist-info/top_level.txt
rbczpremiumapi-1.0.2.dist-info/RECORD
