Metadata-Version: 2.4
Name: rbczpremiumapi
Version: 1.0.2
Summary: Python client library for Raiffeisen Bank Czech Republic Premium API
Home-page: https://github.com/Vitexus/python-rbczpremiumapi
Author: VitexSoftware
Author-email: info@vitexsoftware.cz
Keywords: RBC,Raiffeisen,Bank,API,Premium,OpenAPI,mTLS,PKCS12
License-File: LICENSE
License-File: AUTHORS.md
Requires-Dist: urllib3<3.0.0,>=2.1.0
Requires-Dist: python-dateutil>=2.8.2
Requires-Dist: pydantic>=2
Requires-Dist: typing-extensions>=4.7.1
Dynamic: author
Dynamic: author-email
Dynamic: description
Dynamic: description-content-type
Dynamic: home-page
Dynamic: keywords
Dynamic: license-file
Dynamic: requires-dist
Dynamic: summary
